{
  "project_info": {
    "project_number": "180012197883",
    "project_id": "filmawy-8fae4",
    "storage_bucket": "filmawy-8fae4.appspot.com"
  },
  "client": [
    {
      "client_info": {
        "mobilesdk_app_id": "1:180012197883:android:9a7881f7c22a9d94a04d5e",
        "android_client_info": {
          "package_name": "com.dal4.filmawy"
        }
      },
      "oauth_client": [
        {
          "client_id": "180012197883-ktlheuc0rm928rpou0pdk154dugl99jf.apps.googleusercontent.com",
          "client_type": 3
        }
      ],
      "api_key": [
        {
          "current_key": "AIzaSyAdz3zbvzC-vaqIi7nV61uKwqo1UxYrEvU"
        }
      ],
      "services": {
        "appinvite_service": {
          "other_platform_oauth_client": [
            {
              "client_id": "180012197883-ktlheuc0rm928rpou0pdk154dugl99jf.apps.googleusercontent.com",
              "client_type": 3
            }
          ]
        }
      }
    }
  ],
  "configuration_version": "1"
}